pull_request/__init__.py
pull_request/__main__.py
pull_request/command_line_argument_parser.py
pull_request/credential_manager.py
pull_request/exceptions.py
pull_request/main.py
pull_request/pullrequest.py
pull_requests-1.1.2.dist-info/LICENSE
pull_requests-1.1.2.dist-info/METADATA
pull_requests-1.1.2.dist-info/WHEEL
pull_requests-1.1.2.dist-info/entry_points.txt
pull_requests-1.1.2.dist-info/top_level.txt
pull_requests-1.1.2.dist-info/RECORD
