Metadata-Version: 2.1
Name: pull-requests
Version: 1.1.2
Summary: A command line interface for creating pull requests
Author: Hícaro Dânrlley
Author-email: hdanrlley1@gmail.com
Requires-Python: >=3.10
License-File: LICENSE
Requires-Dist: requests
